mediabyte/LICENSE
mediabyte/README.md
mediabyte/__init__.py
mediabyte/hashes_i_have_seen.json
mediabyte/requirements.txt
mediabyte/test_fast.py
mediabyte/atomSyntaxHighlighting/readme.txt
mediabyte/atomSyntaxHighlighting/language-yno/package.json
mediabyte/atomSyntaxHighlighting/language-yno/grammars/mylanguage.cson
mediabyte/files/__init__.py
mediabyte/files/bit.py
mediabyte/files/bit_fuzz.py
mediabyte/files/bno.py
mediabyte/files/cnf.py
mediabyte/files/dl2.py
mediabyte/files/filters.json
mediabyte/files/hashes_i_have_seen.json
mediabyte/files/http_object.py
mediabyte/files/hubby.py
mediabyte/files/lib.py
mediabyte/files/message_object.py
mediabyte/files/mp3Cutter.py
mediabyte/files/omm_file_parser.py
mediabyte/files/online_omm_parser.py
mediabyte/files/ono.py
mediabyte/files/onoObject.py
mediabyte/files/search_srt.py
mediabyte/files/sh.py
mediabyte/files/srt_cli.py
mediabyte/files/srt_keyword_parser.py
mediabyte/files/srt_search_function.py
mediabyte/files/yn.py
mediabyte/files/yno.py
mediabyte/files/yota.py
mediabyte/files/yota_fuzz.py
mediabyte/files/yt_stepper.py
mediabyte/mixtapes/hackers2018.omm
mediabyte/mixtapes/hashes_i_have_seen.json
mediabyte/mixtapes/mixtape24.omm
mediabyte/mixtapes/mixtape_tutorial.omm
mediabyte/mixtapes/multi-line-mixtape.omm
mediabyte/mixtapes/nightmix.omm
mediabyte/srt/Maitre Gims - Copenhagen 22.02.19-YXo-QtDlsXs.en.srt
mediabyte/srt/subtitles_downloaded_goes_in_this_folder.txt
mediabyte/user_guide/Demo: Basic Mixtape operations.ipynb
mediabyte/user_guide/Demo: Cue shifting.ipynb
mediabyte/user_guide/Demo: Mediabyte Hash Referencing.ipynb
mediabyte/user_guide/Demo: Mixtape Arbitrary White-Space.ipynb
mediabyte/user_guide/Demo: Mixtape from omm file.ipynb
mediabyte/user_guide/Demo: One-line YouTube search to VLC playback.ipynb
mediabyte/user_guide/Demo: Online .omm support.ipynb
mediabyte/user_guide/Demo: Playback.ipynb
"mediabyte/user_guide/Demo: Sample skipping, extending and splitting.ipynb"
mediabyte-0.9.1.5.dist-info/AUTHORS.rst
mediabyte-0.9.1.5.dist-info/LICENSE
mediabyte-0.9.1.5.dist-info/METADATA
mediabyte-0.9.1.5.dist-info/WHEEL
mediabyte-0.9.1.5.dist-info/top_level.txt
mediabyte-0.9.1.5.dist-info/RECORD
