Metadata-Version: 2.1
Name: mediabyte
Version: 0.9.1.5
Summary: Mediabyte - a succinct syntax for handling online media
Home-page: https://github.com/taext/mediabyte
Author: David Mekonnen Rønn
Author-email: gh@v1d.dk
License: UNKNOWN
Keywords: online media metadata organizing tagging streaming mixing sharing
Platform: UNKNOWN
Classifier: Development Status :: 4 - Beta
Classifier: Intended Audience :: Developers
Classifier: Intended Audience :: Information Technology
Classifier: Intended Audience :: Science/Research
Classifier: Natural Language :: English
Classifier: Programming Language :: Python :: 3
Classifier: Topic :: Multimedia :: Video :: Non-Linear Editor
Classifier: Topic :: Multimedia :: Sound/Audio
Classifier: Operating System :: POSIX :: Linux
Classifier: Operating System :: Microsoft :: Windows :: Windows 10
